{
 "youtube_id": "cfUqfxj_v1U",
 "title": "Living in Lafayette Vlog 7-12-2013",
 "url": "https://youtu.be/cfUqfxj_v1U",
 "published_at": "2013-07-12",
 "channel": "Kyle Pounds (main)",
 "enrichment": null,
 "claims": [],
 "transcript": [
  {
   "start": 0.0,
   "end": 29.36,
   "text": "Hello, living in Lafayette V-Log, the, ooh, my watch battery died, I don't know what, what is it, uh, 13th, uh, anyways, um, I, uh, I, uh, I lost internet, ooh, the neighbors, uh, couldn't afford to keep up with their internet, so I just called, um, because they were getting all these, like, charges, because they have out of state or something like that, so,"
  },
  {
   "start": 30.0,
   "end": 58.26,
   "text": "I just called their internet service provider, uh, CenturyLink, and, uh, I, I hooked up internet for myself, and, uh, so we're just gonna share the internet, but, uh, the modem will be in my, my house now, so, uh, it's, like, $41 or something, so the lady said, so, 20 megabytes upload and, like, six, seven hundred kilobytes or something, uh, upload and 20 megabytes download, so, anyway,"
  },
  {
   "start": 58.26,
   "end": 68.34,
   "text": "With the modem right next to me, though, it'll make it so I can upload videos a lot faster, that'll be cool, because I was uploading videos on it all day long, for, like, 12 hours, and still didn't upload all the videos, and, uh,"
  },
  {
   "start": 69.22,
   "end": 80.26,
   "text": "And then I lost internet before I even uploaded the final video, so, it's gonna be cool to be uploading videos faster, it'll motivate me to make more, maybe I should just go nuts and, like, upload about an hour a day of talking,"
  },
  {
   "start": 80.26,
   "end": 91.16,
   "text": "But, um, yeah, so, uh, I'll have internet on Wednesday, so I don't think I'll be uploading videos until then, but, uh, today I'll upload this video,"
  },
  {
   "start": 91.24,
   "end": 96.62,
   "text": "Because I'm gonna go to the library to do some work on the internet, um, because it's only a few blocks down,"
  },
  {
   "start": 98.04,
   "end": 105.24,
   "text": "I can still do work on my timeline without internet, but it's, there's only certain things I can do,"
  },
  {
   "start": 105.24,
   "end": 115.46,
   "text": "So it's a lot better if I have internet, um, so, uh, um, yesterday I worked, did two houses,"
  },
  {
   "start": 115.66,
   "end": 121.26,
   "text": "And then we went over, and I got, like, I smoked this weed, no, no, it wasn't even a weed,"
  },
  {
   "start": 121.34,
   "end": 126.48,
   "text": "It was, like, this green, like, sludge stuff, like, green goo,"
  },
  {
   "start": 127.18,
   "end": 132.9,
   "text": "That's, like, supposed to be called, like, uh, I don't even know what it's called, butter or something,"
  },
  {
   "start": 132.9,
   "end": 138.06,
   "text": "Anyways, you, like, heat up this, like, spoon thing, and then you dip it in,"
  },
  {
   "start": 138.58,
   "end": 143.42,
   "text": "And I had, like, two hits, oh my god, I got so high, I got the highest I've ever been at Mark"
  },
  {
   "start": 143.42,
   "end": 149.8,
   "text": "For a long time, um, like, I was, like, out of control high, and then I rode home 13 miles,"
  },
  {
   "start": 149.94,
   "end": 152.9,
   "text": "But I had, like, energy issues, then I got home, and I was just shot,"
  },
  {
   "start": 153.92,
   "end": 161.94,
   "text": "Then I went in, and, um, I had the munchies hardcore, I went and bought, like, my 30 popsicles,"
  },
  {
   "start": 161.94,
   "end": 170.74,
   "text": "And then these other popsicles, and then I got grapes, and, uh, strawberries, and an avocado,"
  },
  {
   "start": 171.32,
   "end": 176.44,
   "text": "And, uh, and was eating that, and then I had the munchies, that was, like, 14 bucks,"
  },
  {
   "start": 176.48,
   "end": 182.3,
   "text": "And then I had the munchies again, so I went out and got a, a, uh, uh, Wendy's meal,"
  },
  {
   "start": 182.42,
   "end": 186.06,
   "text": "Because I hadn't had Wendy's for, like, years, and I was, like, all right, let's just go to the,"
  },
  {
   "start": 186.1,
   "end": 188.54,
   "text": "Each of the fast food restaurants in the neighborhood just once,"
  },
  {
   "start": 188.54,
   "end": 196.62,
   "text": "I've done good times, Subway, McDonald's, and, uh, Burger King so far, uh, and Wednesday's,"
  },
  {
   "start": 196.7,
   "end": 203.26,
   "text": "But, uh, but I was out, I was exhausted, then I slept in until, like, 11.30, I don't know what"
  },
  {
   "start": 203.26,
   "end": 207.84,
   "text": "Happened, I don't think maybe I didn't eat well the day before yesterday, because all I had to eat"
  },
  {
   "start": 207.84,
   "end": 212.16,
   "text": "That whole day was my oatmeal breakfast, and then I had, like, a bag of chips at night,"
  },
  {
   "start": 212.22,
   "end": 216.78,
   "text": "And that was all I ate, so, yeah, if you don't eat anything the day before,"
  },
  {
   "start": 216.78,
   "end": 221.34,
   "text": "And then all of a sudden you exercise, and, like, you know, I rode 10 miles,"
  },
  {
   "start": 221.56,
   "end": 224.08,
   "text": "And then I got a flat, but they picked me up on the way there,"
  },
  {
   "start": 224.24,
   "end": 230.58,
   "text": "Luckily I got a flat at the right place, but, um, I mean, if you don't do anything for, like,"
  },
  {
   "start": 230.62,
   "end": 234.68,
   "text": "A week and a half, and then all of a sudden you ride, like, 23 miles,"
  },
  {
   "start": 234.78,
   "end": 238.2,
   "text": "And then you work for, like, a few hours, you know, like, labor, hard labor,"
  },
  {
   "start": 238.2,
   "end": 243.9,
   "text": "The body will, it's kind of like doing a hundred mile ride to a normal person, so,"
  },
  {
   "start": 244.86,
   "end": 255.2,
   "text": "Yeah, woof, doozy, but, uh, anyway, oh, shit, I'm yawning, I'm yawning, so, uh, yeah,"
  },
  {
   "start": 255.42,
   "end": 261.12,
   "text": "Gonna go into the library right now, I'm gonna have breakfast first, and then, yeah, uh, eat some,"
  },
  {
   "start": 261.12,
   "end": 266.54,
   "text": "Um, do some work on my timeline, not internet connected, and then go in the library and work"
  },
  {
   "start": 266.54,
   "end": 272.98,
   "text": "Until they close, but then I won't be able to eat my popsicles, so, whatever, okay, peace out."
  }
 ]
}