{
 "youtube_id": "en8ATShTj6k",
 "title": "Trump's Tarrifs in light of annexing countries -  Request",
 "url": "https://youtu.be/en8ATShTj6k",
 "published_at": "2025-03-13",
 "channel": "Kyle Pounds (main)",
 "enrichment": {
  "summary": "Kyle responds to a viewer request to revisit his thoughts on Trump's annexation ambitions (Greenland, Canada, Panama Canal) now in light of Trump's tariffs. He argues both moves stem from the same pattern: an unqualified person in power who doesn't know how to govern, so they act chaotically. He expresses general support for the idea of tariffs to rebuild American manufacturing but thinks Trump is the wrong person to execute them. He then expands into a long digression on Greek/Roman political philosophy, class systems, meritocracy, and his idea of a history-test-based UBI system.",
  "speaker": "kyle",
  "topics": [
   "Trump tariffs",
   "annexation of Greenland/Canada/Panama",
   "tariff policy pros and cons",
   "Greek/Roman political philosophy",
   "class systems and aristocracy",
   "meritocracy",
   "Elon Musk and tech billionaires in politics",
   "history as policy guide",
   "UBI and history test idea",
   "YouTube likes complaint"
  ],
  "stances": [
   {
    "topic": "Trump's annexation ambitions",
    "position": "symptom of an unqualified leader who doesn't know how to govern, so he upends things just to seem consequential"
   },
   {
    "topic": "Tariffs in general",
    "position": "personally supports the general idea of tariffs to bring manufacturing back to America and reduce global shipping"
   },
   {
    "topic": "Trump implementing tariffs",
    "position": "wrong person to do it — doing it all at once chaotically without understanding will cause economic damage"
   },
   {
    "topic": "Billionaires in power (Musk, Thiel, Trump)",
    "position": "market/engineer class pretending to be aristocrats — their skill set is making money, not governing, and it leads to societal harm"
   },
   {
    "topic": "Taxing the wealthy",
    "position": "explicitly supports 90% top tax rates and believes there should be no billionaires"
   },
   {
    "topic": "Class systems",
    "position": "favors a merit-based aristocracy rooted in education and statecraft, not inherited wealth or market success"
   },
   {
    "topic": "UBI tied to a history test",
    "position": "advocates giving UBI to people who pass a history test as a way to create a true meritocracy"
   },
   {
    "topic": "Trump's historical parallels",
    "position": "compares Trump directly to Commodus and Caligula based on vanity and ignorance of history"
   }
  ],
  "entities": [
   "Trump",
   "Elon Musk",
   "Katie/KD655/K9365 (viewer)",
   "Sam Seder",
   "Peter Thiel",
   "Michael Knowles",
   "Napoleon",
   "Marcus Aurelius",
   "Antoninus Pius",
   "Commodus",
   "Caligula",
   "Stilicho",
   "Plato",
   "Aristotle",
   "Solon",
   "Homer",
   "Joe Rogan",
   "Greenland",
   "Canada",
   "Panama Canal",
   "China",
   "Scandinavia",
   "Rome",
   "Ancient Greece",
   "Egypt",
   "Tibet",
   "Mexico",
   "Gulf of Mexico",
   "Marshall Plan",
   "World War II",
   "Chip Act (Biden)"
  ],
  "date": "",
  "model": "sonnet"
 },
 "claims": [],
 "transcript": [
  {
   "start": 0.46,
   "end": 5.6,
   "text": "Hi here's a request video I just got done yapping forever about my vlog so I figured I would do a"
  },
  {
   "start": 5.6,
   "end": 14.0,
   "text": "Request this is from like katie 69 655 whatever who is kind of the only person giving me request"
  },
  {
   "start": 14.0,
   "end": 18.66,
   "text": "Videos now and I don't know why see they gave me a request video what do I think about trump"
  },
  {
   "start": 18.66,
   "end": 27.36,
   "text": "Wanting to invade um um annex greenland canada and panama canal and then I did a video about it"
  },
  {
   "start": 27.36,
   "end": 32.46,
   "text": "And they were like thanks and they don't I don't know if they like my videos or not and this is"
  },
  {
   "start": 32.46,
   "end": 39.78,
   "text": "Directly to you but like if you like my videos like youtube is taking them away because none of my"
  },
  {
   "start": 39.78,
   "end": 44.68,
   "text": "Videos get likes I got like a like yesterday but if I look at it now it might have been taken away"
  },
  {
   "start": 44.68,
   "end": 57.0,
   "text": "Um so if you're going to give me a via um a request kd 655 um k k9 365 um"
  },
  {
   "start": 57.0,
   "end": 63.34,
   "text": "Then like my video and I would appreciate it if you even say in the comments you liked it because"
  },
  {
   "start": 63.34,
   "end": 69.02,
   "text": "I want to know definitively if youtube is taking away likes because I see all the time I see there's"
  },
  {
   "start": 69.02,
   "end": 75.62,
   "text": "A like and then I look at the video the next day and it's gone so anyway but then they comment back"
  },
  {
   "start": 75.62,
   "end": 81.82,
   "text": "And they're like do the video about do the video again only in the light of the uh the tariffs so"
  },
  {
   "start": 81.82,
   "end": 87.04,
   "text": "It's like is this like a trick question like are you looking for a specific answer and if I answer"
  },
  {
   "start": 87.04,
   "end": 95.08,
   "text": "It correctly I get the prize or something so what do I think about donald trump annexing wanting to"
  },
  {
   "start": 95.08,
   "end": 105.24,
   "text": "Annex greenland canada and panama and and went in in in the context of all of his tariffs um okay so"
  },
  {
   "start": 105.24,
   "end": 110.6,
   "text": "I'll basically say the same thing and I'll expand as I did the first time okay the first time I said"
  },
  {
   "start": 110.6,
   "end": 118.4,
   "text": "The reason he's doing that is that's the kind of stuff that people do who um don't who are in a"
  },
  {
   "start": 118.4,
   "end": 125.94,
   "text": "Governing job who don't know how to govern because he has no um he doesn't realize that being a good"
  },
  {
   "start": 125.94,
   "end": 131.1,
   "text": "President sometimes being a good president all you have to do is not do anything like you can just"
  },
  {
   "start": 131.1,
   "end": 137.74,
   "text": "Stop bad laws from being made like maybe you happen to be in the perfect part of history where"
  },
  {
   "start": 137.74,
   "end": 143.76,
   "text": "There's nothing wrong and so then your job as president is just to keep it right like there was"
  },
  {
   "start": 143.76,
   "end": 151.12,
   "text": "A there was a period for like 10 years like in the 160s I think it was the 150s of the roman empire there"
  },
  {
   "start": 151.12,
   "end": 163.52,
   "text": "Was no war for an entire decade under um I think it was like pi uh pious antoninus pious but um like"
  },
  {
   "start": 163.52,
   "end": 170.8,
   "text": "Right before um the macromani war started with um uh uh uh marcus aurelius and then they had the"
  },
  {
   "start": 170.8,
   "end": 176.24,
   "text": "The plague and then it all started to go hell you know with commodus after that so that was like the"
  },
  {
   "start": 176.24,
   "end": 182.7,
   "text": "Calm before the storm but um you know maybe you know then that would be somebody with a good sense"
  },
  {
   "start": 182.7,
   "end": 190.1,
   "text": "Of um self-worth and they don't have to do anything so if somebody like you know wants to"
  },
  {
   "start": 190.1,
   "end": 196.38,
   "text": "You don't know what to do right because you're a dumbass then what you do and you're a spoiled brat"
  },
  {
   "start": 196.38,
   "end": 202.4,
   "text": "Then what you do is you just up up in the apple cart because that's what you know that's what like"
  },
  {
   "start": 202.4,
   "end": 208.22,
   "text": "All the smartest people in the past that's what they did they upended the apple cart like they"
  },
  {
   "start": 208.22,
   "end": 213.14,
   "text": "Invented a new thing and then they brought it in so he's like oh cool I want to like invent something"
  },
  {
   "start": 213.14,
   "end": 218.84,
   "text": "New then you know like how newton invented gravity he's like oh yeah I'll invent I'll do something new"
  },
  {
   "start": 218.84,
   "end": 222.3,
   "text": "Because I'm strong and you know everybody else they hadn't been doing anything so"
  },
  {
   "start": 222.3,
   "end": 228.06,
   "text": "Invade a country because none of my predecessors had the balls to it's basically like that"
  },
  {
   "start": 228.06,
   "end": 236.3,
   "text": "It's like oh they got a bad deal we gave it back to to panama and now the chinese run it and so we"
  },
  {
   "start": 236.3,
   "end": 241.98,
   "text": "Just take it back because uh the other one didn't have the balls and so then you would yeah so then"
  },
  {
   "start": 241.98,
   "end": 246.08,
   "text": "You just do all sorts of stuff like that and that's the same reason he's doing the the the tariffs"
  },
  {
   "start": 246.08,
   "end": 256.34,
   "text": "Is is he knows that um that um you know he's got the notion that america has been you know paying"
  },
  {
   "start": 256.34,
   "end": 262.46,
   "text": "Too much you know like we were paying for we were policing the world for free and so and then we get"
  },
  {
   "start": 262.46,
   "end": 266.9,
   "text": "The bad trade and we help these other countries come up and their gdp comes up and now we're"
  },
  {
   "start": 266.9,
   "end": 272.12,
   "text": "Importing from them and yeah there's there's and so then you use trades to fix it and so there's"
  },
  {
   "start": 272.12,
   "end": 279.08,
   "text": "You know an argument I think there's an argument to be made in general about using tariffs to stop"
  },
  {
   "start": 279.08,
   "end": 286.86,
   "text": "Imports you know like people say but the problem is you don't want donald trump to do that you know"
  },
  {
   "start": 286.86,
   "end": 293.0,
   "text": "Like if anybody anybody else any statesman were to do it yeah sure experiment with donald trump it's"
  },
  {
   "start": 293.0,
   "end": 299.08,
   "text": "Just a it's just a disaster but now that I'm done contextualizing with donald trump let me just say"
  },
  {
   "start": 299.08,
   "end": 304.74,
   "text": "In general that the tariffs like you know there's two schools of thought there's like the donald trump"
  },
  {
   "start": 304.74,
   "end": 310.58,
   "text": "Idea and then there's what the other liberals you know the people who disagree with them say so"
  },
  {
   "start": 310.58,
   "end": 318.52,
   "text": "You know they say that like when you get when you charge the extra tariffs like the um the people in"
  },
  {
   "start": 318.52,
   "end": 325.06,
   "text": "America end up paying those tariffs like we pay the tariffs and well and well yeah that's true for"
  },
  {
   "start": 325.06,
   "end": 333.42,
   "text": "That particular thing from that country um they would pass the tariff on to us and then that thing"
  },
  {
   "start": 333.42,
   "end": 338.24,
   "text": "Becomes more expensive and then you can decide if you want to pay extra because it comes from a"
  },
  {
   "start": 338.24,
   "end": 344.48,
   "text": "Country you know and so basically by adding tariffs on everything that's basically trying to um force"
  },
  {
   "start": 344.48,
   "end": 351.62,
   "text": "The americans to make our own stuff you know because it because it gives uh a um an opportunity"
  },
  {
   "start": 351.62,
   "end": 359.28,
   "text": "For the people in the made in america people to make money um and then and then the other countries"
  },
  {
   "start": 359.28,
   "end": 368.02,
   "text": "Want to retaliate with their trade war by adding their tariffs and that's great um now if you do"
  },
  {
   "start": 368.02,
   "end": 373.84,
   "text": "It all at once like a dumbass you know like how trump and elon musk are going around firing all of these"
  },
  {
   "start": 373.84,
   "end": 379.24,
   "text": "Government workers and trying to cut social benefits and gutting the uh the government and the education"
  },
  {
   "start": 379.24,
   "end": 383.92,
   "text": "Department and that's bad um and then if you do that suddenly and you don't know what you're doing"
  },
  {
   "start": 383.92,
   "end": 390.22,
   "text": "With tariffs yeah that cause problems but um I mean I personally I don't know any other way I think"
  },
  {
   "start": 390.22,
   "end": 396.44,
   "text": "That's the easiest way to kind of force us to just build stuff here and I think we should build more"
  },
  {
   "start": 396.44,
   "end": 402.1,
   "text": "Things here you know like um the steel most of our steel is being built in china we should bring the"
  },
  {
   "start": 402.1,
   "end": 408.66,
   "text": "Steel manufacturing back here um uh biden did the chip act because the chips were being built in china"
  },
  {
   "start": 408.66,
   "end": 415.3,
   "text": "So we can bring the chips back here and then if you add tariffs you know then the stuff from china"
  },
  {
   "start": 415.3,
   "end": 421.68,
   "text": "Gets more expensive and then china wants to add tariffs on us so then we can't send stuff to china"
  },
  {
   "start": 421.68,
   "end": 425.5,
   "text": "So then we would send it to us instead and then we wouldn't buy stuff from china we'd buy it from us"
  },
  {
   "start": 425.5,
   "end": 430.7,
   "text": "And overall I think that's the trend that we should be going to I actually like the general idea of the"
  },
  {
   "start": 430.7,
   "end": 440.34,
   "text": "Tariffs because um because world trade um when the world gets more insecure as it's getting um we'll"
  },
  {
   "start": 440.34,
   "end": 445.78,
   "text": "Get less predictable and harder to um to police and easier for crime criminals to take over"
  },
  {
   "start": 445.78,
   "end": 451.76,
   "text": "Shipping ships also it's too expensive for all the shipping ships to travel all over the world and"
  },
  {
   "start": 451.76,
   "end": 457.64,
   "text": "This diesel fuel that pollutes the earth uses up all of our our natural resources we don't have the"
  },
  {
   "start": 457.64,
   "end": 461.96,
   "text": "Most you know it's a finite source our goyle it doesn't get replenished what are we going to do"
  },
  {
   "start": 461.96,
   "end": 466.3,
   "text": "You know when we're done with it we have to figure out another way to get energy and so we should try"
  },
  {
   "start": 466.3,
   "end": 473.14,
   "text": "To let it stretch out and so do less trade and more local and locally in the country and then we can have"
  },
  {
   "start": 473.14,
   "end": 482.46,
   "text": "All you know it brings lots of good results from that brings in local um um culture back you know"
  },
  {
   "start": 482.46,
   "end": 487.54,
   "text": "Local different different flavors of different parts of the world instead of everybody being cookie"
  },
  {
   "start": 487.54,
   "end": 493.56,
   "text": "Cutter the exact same makes people um easier to start little businesses um and be entrepreneur"
  },
  {
   "start": 493.56,
   "end": 498.84,
   "text": "When when it's not you know huge companies over owning the whole world it's uh you know that you"
  },
  {
   "start": 498.84,
   "end": 503.14,
   "text": "Have the tariff then you could have any of the interstate tariffs which I think would be a good"
  },
  {
   "start": 503.14,
   "end": 510.76,
   "text": "Idea and and then um you know locals could uh you could have more of more of a community people could"
  },
  {
   "start": 510.76,
   "end": 519.68,
   "text": "Um you know uh become more ingrained in their local uh community like people need to own houses more"
  },
  {
   "start": 519.68,
   "end": 523.98,
   "text": "Right like because then you could personalize your house if nobody owns their house then everybody has"
  },
  {
   "start": 523.98,
   "end": 529.5,
   "text": "To live in a room that looks like this like boring you know like I have this room as my rental room"
  },
  {
   "start": 529.5,
   "end": 534.26,
   "text": "That I can't get anybody to move in with because my the rest of my apartment is too personalized"
  },
  {
   "start": 534.26,
   "end": 546.5,
   "text": "But um but um so anyways um but here's the problem um you don't want the wrong people who don't know"
  },
  {
   "start": 546.5,
   "end": 551.0,
   "text": "What they're doing to just arbitrarily do it like there's a science to it and this is another thing"
  },
  {
   "start": 551.0,
   "end": 554.96,
   "text": "That I wanted to talk about and I think I'll throw it in with this video because I'm talking about how"
  },
  {
   "start": 554.96,
   "end": 564.5,
   "text": "People who are like unqualified are in positions of um you know power um that took a different type"
  },
  {
   "start": 564.5,
   "end": 568.6,
   "text": "Of a person right so we live in a world that should take a different type of person we live in a world"
  },
  {
   "start": 568.6,
   "end": 576.78,
   "text": "Right now where the rich person gets to be the statesman so so it's like everybody wants to be a"
  },
  {
   "start": 576.78,
   "end": 583.76,
   "text": "Statesman or but they're not they're just pretending to so you get like elon musk for example so he's not"
  },
  {
   "start": 583.76,
   "end": 588.3,
   "text": "A statesman because you want to you want to judge somebody judge them based on where they were from"
  },
  {
   "start": 588.3,
   "end": 594.52,
   "text": "The beginning and this is how you can compare um our society with ancient greece um so because like"
  },
  {
   "start": 594.52,
   "end": 600.96,
   "text": "Elon musk well he's a computer nerd like that's how he made his money that's who he is he he went on"
  },
  {
   "start": 600.96,
   "end": 605.42,
   "text": "The computer and he figured out um like the banking and the credit cards and he did paypal"
  },
  {
   "start": 605.42,
   "end": 611.02,
   "text": "And then he made a bunch of money from the paypal and then he bought another business and he was good"
  },
  {
   "start": 611.02,
   "end": 616.22,
   "text": "And he and he ended up becoming part of the investment investor class and got really rich"
  },
  {
   "start": 616.22,
   "end": 624.36,
   "text": "And um so he's a computer nerd and so now he but he but but now he's he's a statesman because he"
  },
  {
   "start": 624.36,
   "end": 628.98,
   "text": "Started out as a computer girl I got a bunch of money and then he's like oh let me make more money"
  },
  {
   "start": 628.98,
   "end": 634.78,
   "text": "So I'll pretend to be a statesman so I can make more money and so that's where all hell goes to break"
  },
  {
   "start": 634.78,
   "end": 641.24,
   "text": "Goes loose and this is where the greeks um had it figure out better than we did the greek"
  },
  {
   "start": 641.24,
   "end": 648.56,
   "text": "Civilization wasn't older than ours um much younger in fact you know the greek civilization in the time"
  },
  {
   "start": 648.56,
   "end": 653.12,
   "text": "Of plato who was like 600 bc had only been around for a couple hundred years like they had the"
  },
  {
   "start": 653.12,
   "end": 662.72,
   "text": "They had the fall in uh 1185 like with troy the dark ages of greece began the the bronze age collapse"
  },
  {
   "start": 662.72,
   "end": 669.76,
   "text": "Due to like uh probably a volcano that blew up and then stopped it caused droughts and then everybody"
  },
  {
   "start": 669.76,
   "end": 677.0,
   "text": "Uh everybody crashed all of the empires um hittites egyptians and all the greeks"
  },
  {
   "start": 677.0,
   "end": 682.54,
   "text": "And they had 400 years of darkness and then and then they started to um"
  },
  {
   "start": 682.54,
   "end": 692.2,
   "text": "They started to uh uh get their civilization back kind of like in the time of like um homer lived in"
  },
  {
   "start": 692.2,
   "end": 697.04,
   "text": "The 800s and then he had the seven sages in the 700s and that the cities were kind of founded"
  },
  {
   "start": 697.04,
   "end": 704.26,
   "text": "Athens and sparta in the 700s and rome and then by the 450s you know when plato was around"
  },
  {
   "start": 704.26,
   "end": 712.48,
   "text": "Um so they had been maybe 300 300 or 400 year old culture society rebooted um unless you're"
  },
  {
   "start": 712.48,
   "end": 718.32,
   "text": "Talking and they were kind of adjacent to um egypt unless you're talking about egypt in which case"
  },
  {
   "start": 718.32,
   "end": 726.42,
   "text": "Um during at the time of plato egypt was four times older than our culture like you could say"
  },
  {
   "start": 726.42,
   "end": 733.68,
   "text": "Our culture was 2500 years old starting with plato with all the greeks well 2500 years ago"
  },
  {
   "start": 733.68,
   "end": 742.24,
   "text": "Um egyptian culture was already 10 000 years old uh because that's what plato said that's what"
  },
  {
   "start": 742.24,
   "end": 749.26,
   "text": "Plato said the egyptians told solon so 10 000 years even the time of solon but the greeks weren't"
  },
  {
   "start": 749.26,
   "end": 753.86,
   "text": "Egyptians you know only the rich greeks would go there so like they had like a father culture which"
  },
  {
   "start": 753.86,
   "end": 758.74,
   "text": "Was that old but the greeks themselves were only a couple hundred years old however um you know so"
  },
  {
   "start": 758.74,
   "end": 765.26,
   "text": "Kind of like us maybe about as old as us from like um you know the time of like newton you know"
  },
  {
   "start": 765.26,
   "end": 769.9,
   "text": "Um the beginning of america about as old as the america first started getting colonized"
  },
  {
   "start": 769.9,
   "end": 776.88,
   "text": "Um maybe about the same actually as like the dalai lama they like to say like tibet's an ancient"
  },
  {
   "start": 776.88,
   "end": 783.74,
   "text": "Culture well they only started doing those first reincarnations of the lamas like in the 1600s"
  },
  {
   "start": 783.74,
   "end": 792.26,
   "text": "So it's about how old greece was but they were way more um educated than us in terms of politics"
  },
  {
   "start": 792.26,
   "end": 798.5,
   "text": "Because they had the city state so they had like hundreds like a couple hundred of"
  },
  {
   "start": 798.5,
   "end": 804.84,
   "text": "All these different um you know similar culture because they all came from the dorians down"
  },
  {
   "start": 804.84,
   "end": 809.44,
   "text": "Doing trade with each other you know with the boats and all that kind of stuff who knew about each"
  },
  {
   "start": 809.44,
   "end": 816.98,
   "text": "Other and but each city state had a completely different political system so they so they were"
  },
  {
   "start": 816.98,
   "end": 822.98,
   "text": "Just very educated about all the different political systems and ramifications and so that's"
  },
  {
   "start": 822.98,
   "end": 828.96,
   "text": "What you read about in aristotle's politics all the different political systems and how they change"
  },
  {
   "start": 828.96,
   "end": 835.02,
   "text": "And how they morph and move and and you know that's when he talks about the cycle of the politics"
  },
  {
   "start": 835.02,
   "end": 840.04,
   "text": "Like first into a kingdom and then and then it turns into an oligarchy and then they fix it and"
  },
  {
   "start": 840.04,
   "end": 844.4,
   "text": "It turns into an aristocracy and then it gets better turns into a democracy but then it becomes if it"
  },
  {
   "start": 844.4,
   "end": 850.56,
   "text": "Becomes too much of a democracy it turns back into a tyranny which then turns into uh an oligarchy and"
  },
  {
   "start": 850.56,
   "end": 855.84,
   "text": "Then you and then aristocracy and then democracy and you just go around so you're always trying to find"
  },
  {
   "start": 855.84,
   "end": 859.96,
   "text": "The balance and that's why rome was was so popular because they had the perfect balance between the"
  },
  {
   "start": 859.96,
   "end": 867.18,
   "text": "Three the democracy the three good forms of forms of government democracy aristocracy and kingship"
  },
  {
   "start": 867.18,
   "end": 871.22,
   "text": "Because there's six forms of government three good and three bad the good would be aristocracy"
  },
  {
   "start": 871.22,
   "end": 878.96,
   "text": "That's bad counterpart oligarchy the good is um um democracy bad bad bad side of that tyranny"
  },
  {
   "start": 878.96,
   "end": 892.96,
   "text": "Um the good is um kingship bad side of that um oligarchy or tyranny so um anyway um so they knew um"
  },
  {
   "start": 892.96,
   "end": 900.12,
   "text": "Uh they knew all that all the different positives but another thing that they knew that we don't know"
  },
  {
   "start": 900.12,
   "end": 905.58,
   "text": "And I guess the europeans haven't really figured out and that's the kind of the difference between"
  },
  {
   "start": 905.58,
   "end": 912.88,
   "text": "American europe is the classes the different classes so america uh because we're kind of uh going"
  },
  {
   "start": 912.88,
   "end": 918.4,
   "text": "Back into the class system again where it's overly classes but it's based off of money and that's where"
  },
  {
   "start": 918.4,
   "end": 926.32,
   "text": "You're not going to uh do you have a very positive um a very healthy society like the roman empire wasn't"
  },
  {
   "start": 926.32,
   "end": 932.8,
   "text": "Healthy because it was just based off money and power and so the ancient greeks and even the the"
  },
  {
   "start": 932.8,
   "end": 936.86,
   "text": "Egyptians um and I think they got it from the egyptians because egyptians had a system too but"
  },
  {
   "start": 936.86,
   "end": 944.26,
   "text": "The ancient greeks have data um had a very distinct class system of different classes and the highest"
  },
  {
   "start": 944.26,
   "end": 950.26,
   "text": "Classes system were the landowners they were like the aristocracy and the reason that you wanted an"
  },
  {
   "start": 950.26,
   "end": 957.68,
   "text": "Aristocracy of landowners who made money just from owning the land is so that they could spend all of"
  },
  {
   "start": 957.68,
   "end": 966.12,
   "text": "Their time and energy trying to govern because every single thing that you do is based off of a skill"
  },
  {
   "start": 966.12,
   "end": 974.32,
   "text": "Like every single job like humans are are a I've always been and as we get more and and um forward in"
  },
  {
   "start": 974.32,
   "end": 982.48,
   "text": "Society are a very uh we're a social uh species and but not so much in the way that like an ant is"
  },
  {
   "start": 982.48,
   "end": 985.74,
   "text": "Where you have all the worker bees and they do the same thing we're a social species in that"
  },
  {
   "start": 985.74,
   "end": 992.32,
   "text": "We we have all of these like particular uh jobs of people who who do them their whole lives like"
  },
  {
   "start": 992.32,
   "end": 997.16,
   "text": "The guilds because you become a master everybody's supposed to become a master of one thing you don't"
  },
  {
   "start": 997.16,
   "end": 1004.5,
   "text": "Want to be a mat uh you know a a jack of all trades and a master of none because then you'll never get a"
  },
  {
   "start": 1004.5,
   "end": 1008.9,
   "text": "Job you'll never be able to support yourself because they'll always hire the master to do whatever job"
  },
  {
   "start": 1008.9,
   "end": 1016.06,
   "text": "And so that's why if you're aristocracy and you don't have a job that's because your job is to"
  },
  {
   "start": 1016.06,
   "end": 1022.66,
   "text": "Govern and if you're going to be a good governor you need like it takes you need to be a master of"
  },
  {
   "start": 1022.66,
   "end": 1028.22,
   "text": "It like it takes your whole life of training so you could be born as a kid in the castle and you"
  },
  {
   "start": 1028.22,
   "end": 1032.22,
   "text": "Learn all the different languages and then you learn all the different customs and then you can you can"
  },
  {
   "start": 1032.22,
   "end": 1037.54,
   "text": "Relate to the different people the poor people the rich people and so and the people from your"
  },
  {
   "start": 1037.54,
   "end": 1043.66,
   "text": "Counterparts from the other city states and so like back in those days um plato like would talk"
  },
  {
   "start": 1043.66,
   "end": 1047.68,
   "text": "About a slave like you couldn't trust the slave and they're bad and it's like nowadays you'd be"
  },
  {
   "start": 1047.68,
   "end": 1053.4,
   "text": "Like well that's not fair treat everybody equally but he looked at it pragmatically like no you"
  },
  {
   "start": 1053.4,
   "end": 1058.48,
   "text": "Couldn't because they they weren't trained that way they weren't raised that way they were raised to"
  },
  {
   "start": 1058.48,
   "end": 1063.38,
   "text": "Survive and so you know if you put a candy in front of a baby they'll take it same thing with the"
  },
  {
   "start": 1063.38,
   "end": 1072.2,
   "text": "Slave like and so you can't just get a slave to all of a sudden become a um uh the the aristocrat"
  },
  {
   "start": 1072.2,
   "end": 1077.26,
   "text": "You know and if you did that that you would get like there's history is full of ex-slaves who became"
  },
  {
   "start": 1077.26,
   "end": 1085.9,
   "text": "Aristocrats and then destroyed the whole society like stilicho um like the eunuchs of the of china and"
  },
  {
   "start": 1085.9,
   "end": 1094.0,
   "text": "Of um end of um the ottoman empire reaping havoc and all that kind of stuff um so in ancient greece"
  },
  {
   "start": 1094.0,
   "end": 1099.22,
   "text": "They had like the different classes for reasons and that they didn't have they had different orders"
  },
  {
   "start": 1099.22,
   "end": 1104.64,
   "text": "Of them like first to lowest so the highest was the aristocrat the statesman who was supposed to be"
  },
  {
   "start": 1104.64,
   "end": 1112.56,
   "text": "Educated well read below him was like um was like a mechanic so like an engineer so you want to you"
  },
  {
   "start": 1112.56,
   "end": 1117.48,
   "text": "Want to make them connected to them to the current current world that's what I'm trying to do below"
  },
  {
   "start": 1117.48,
   "end": 1123.62,
   "text": "That was like the engineer so they were like smart they could fix things but they were not as high as"
  },
  {
   "start": 1123.62,
   "end": 1130.28,
   "text": "The aristocrat because that wasn't their skill it wasn't their training they were an engineer they were"
  },
  {
   "start": 1130.28,
   "end": 1137.56,
   "text": "Like a mechanic and then below that would be like the trader the businessman over at the over at the"
  },
  {
   "start": 1137.56,
   "end": 1142.88,
   "text": "The market right and so they were they were the third down they weren't very high because in the"
  },
  {
   "start": 1142.88,
   "end": 1146.8,
   "text": "Market you're allowed to lie cheat and steal and you just do whatever you can get away with and so"
  },
  {
   "start": 1146.8,
   "end": 1150.06,
   "text": "They didn't those people weren't respected like you're you're on your own if you're going to the"
  },
  {
   "start": 1150.06,
   "end": 1156.48,
   "text": "Market like fool me once shame on you fool me twice shame on me like like it's just a dog eat dog"
  },
  {
   "start": 1156.48,
   "end": 1160.94,
   "text": "World out there in a market and so that's why they're not the highest they're not the highest class"
  },
  {
   "start": 1160.94,
   "end": 1165.6,
   "text": "Of people or the best people or the you know it's the aristocrats that's why they call the"
  },
  {
   "start": 1165.6,
   "end": 1169.98,
   "text": "Gentleman the gentle you know and then the like they're better people you know because they're"
  },
  {
   "start": 1169.98,
   "end": 1175.82,
   "text": "Trained to be better because they have the whole you know society that depends on them"
  },
  {
   "start": 1175.82,
   "end": 1181.76,
   "text": "When they're good decision making so and then below so that's how it is it's aristocrat on top"
  },
  {
   "start": 1181.76,
   "end": 1188.86,
   "text": "Mechanic below tradesmen below that and then below that would be like manual journeyman laborers like"
  },
  {
   "start": 1188.86,
   "end": 1192.92,
   "text": "The minimum age workers who like work for the tradesmen or whatever and then below that is the"
  },
  {
   "start": 1192.92,
   "end": 1199.46,
   "text": "Slave it would be like well whatever you're a slave you're retarded you're a looney tune you're a"
  },
  {
   "start": 1199.46,
   "end": 1206.98,
   "text": "You're a you're a hermit you're a you're captured from like uh from another city state you know and"
  },
  {
   "start": 1206.98,
   "end": 1215.32,
   "text": "You're a slave that way from a war like and so anyways the problem with today is we we don't know"
  },
  {
   "start": 1215.32,
   "end": 1221.5,
   "text": "That that's not common knowledge of all that and so we're getting we're getting the um the uh the"
  },
  {
   "start": 1221.5,
   "end": 1230.28,
   "text": "Market guy the seller the market tradesman and the mechanic engineer up into the aristocrat zones"
  },
  {
   "start": 1230.28,
   "end": 1236.8,
   "text": "Right and so so somebody and this is how like um in the enlightenment everything got like twisted up"
  },
  {
   "start": 1236.8,
   "end": 1243.94,
   "text": "And that's why um people um um didn't like the new bourgeoisie and the new money and stuff"
  },
  {
   "start": 1243.94,
   "end": 1250.36,
   "text": "And so you have a you know you have like a the the different classes with like the old money and"
  },
  {
   "start": 1250.36,
   "end": 1254.52,
   "text": "The old families who are like everything's going well because everybody's knows their place and"
  },
  {
   "start": 1254.52,
   "end": 1260.26,
   "text": "They're all educated but then if you know if the if it becomes an oligarchy where the people in"
  },
  {
   "start": 1260.26,
   "end": 1267.66,
   "text": "Charge aren't really all that educated or care um then maybe like a a really good um market guy"
  },
  {
   "start": 1267.66,
   "end": 1272.08,
   "text": "Tradesman it becomes the popular and then he turns into a tyrant because he's just he just plays"
  },
  {
   "start": 1272.08,
   "end": 1275.92,
   "text": "People and he lies and cheats and steals he uses all the stuff you learn from working in the markets"
  },
  {
   "start": 1275.92,
   "end": 1283.84,
   "text": "Um and so um or you could become an engineer like you're like you're a really good uh carriage mechanic"
  },
  {
   "start": 1283.84,
   "end": 1290.16,
   "text": "And you got really good and like um like uh but napoleon was a really good artillery guy and then"
  },
  {
   "start": 1290.16,
   "end": 1296.12,
   "text": "He used that skill to become the charge but if you do that then your skill set isn't running grueling"
  },
  {
   "start": 1296.12,
   "end": 1303.18,
   "text": "People your skill set was always what you were and so it's like you can take the um hood the the hood"
  },
  {
   "start": 1303.18,
   "end": 1307.72,
   "text": "Rat out of the hood but you can't take the hood out of the hood rat you know so that's what's happening"
  },
  {
   "start": 1307.72,
   "end": 1317.0,
   "text": "Now you've got peter teal um elon musk all those like you know market guys money guys who cared about"
  },
  {
   "start": 1317.0,
   "end": 1325.24,
   "text": "That um or or engineers who now they have a bunch of money and so now they fancy themselves the aristocrat"
  },
  {
   "start": 1325.24,
   "end": 1330.6,
   "text": "But for all the wrong reasons because they're not an aristocrat they're they just want to make"
  },
  {
   "start": 1330.6,
   "end": 1336.24,
   "text": "Themselves richer and so what we need is to have a system of where we have you know the the ruling"
  },
  {
   "start": 1336.24,
   "end": 1340.94,
   "text": "Class or the smartest people and so some people might go oh yeah well let's just go back to the"
  },
  {
   "start": 1340.94,
   "end": 1348.72,
   "text": "To like uh aristocracy with the the families then because then like the rich wise father can make a good"
  },
  {
   "start": 1348.72,
   "end": 1355.1,
   "text": "Son but that but that doesn't work because rich people have 10 kids like elon musk who they don't"
  },
  {
   "start": 1355.1,
   "end": 1358.36,
   "text": "Talk to and they don't have relationships with so then there's all these super rich people"
  },
  {
   "start": 1358.36,
   "end": 1364.24,
   "text": "Growing up without parents and then they have that wealth and then they have kids but they don't know"
  },
  {
   "start": 1364.24,
   "end": 1368.76,
   "text": "How to raise kids because they weren't raised right kind of like donald trump and his kids you know not"
  },
  {
   "start": 1368.76,
   "end": 1375.86,
   "text": "Having a relationship with him and or with his father and then so that um um those people set the"
  },
  {
   "start": 1375.86,
   "end": 1383.22,
   "text": "Tone for everybody else and so so how do you get the aristocracy class the aristocratic class"
  },
  {
   "start": 1383.22,
   "end": 1389.94,
   "text": "In charge instead of everybody else and america was doing really well for a while by um um by having"
  },
  {
   "start": 1389.94,
   "end": 1396.84,
   "text": "Um you know capitalism and and the system with the government and all the different government"
  },
  {
   "start": 1396.84,
   "end": 1401.9,
   "text": "Agencies and the cream rises to the top and we used to have presidents who were you know"
  },
  {
   "start": 1401.9,
   "end": 1407.86,
   "text": "Who followed the law and um now we're realizing that well if you get a president up there who doesn't"
  },
  {
   "start": 1407.86,
   "end": 1411.7,
   "text": "Follow the law you can just change the law like it was kind of like an honor system and the reason"
  },
  {
   "start": 1411.7,
   "end": 1416.92,
   "text": "It wasn't changed because the president didn't do it and so we need to switch it so that the people"
  },
  {
   "start": 1416.92,
   "end": 1422.82,
   "text": "Become president aren't these people who you can't trust and so how do you do that um you know in a"
  },
  {
   "start": 1422.82,
   "end": 1428.26,
   "text": "Way that that's not like how we did in the past where the old family you know you just turn into a"
  },
  {
   "start": 1428.26,
   "end": 1434.74,
   "text": "Actual meritocracy well you the first thing you would do is use use technology because that's"
  },
  {
   "start": 1434.74,
   "end": 1439.64,
   "text": "Something that never exists in the past so you do you use you you do something that you could never do"
  },
  {
   "start": 1439.64,
   "end": 1444.8,
   "text": "And you have big dreams and so I'd say yeah you use the technology to create the meritocracy"
  },
  {
   "start": 1444.8,
   "end": 1449.94,
   "text": "So like whoever is smartest and well in what then well I would say in stuff having to do a"
  },
  {
   "start": 1449.94,
   "end": 1455.56,
   "text": "Statesmanship well what has to do with statescraft and statesmanship history like let me give you an"
  },
  {
   "start": 1455.56,
   "end": 1463.08,
   "text": "Example um I was listening to um sam cedar today and he was talking about how he debated like 35 um"
  },
  {
   "start": 1463.08,
   "end": 1469.56,
   "text": "Right wingers and he kept talking to all these right wingers he's like really arrogant 20 year"
  },
  {
   "start": 1469.56,
   "end": 1475.56,
   "text": "Olds like republicans talking like sam cedar's like 55 like a professional commentator knows his stuff"
  },
  {
   "start": 1475.56,
   "end": 1480.66,
   "text": "And they're just yapping at him and yelling at him like nonsense like they're these like"
  },
  {
   "start": 1480.66,
   "end": 1486.5,
   "text": "Brainwashed right wing they just say the talking point so he'll say like one kid was trying to say"
  },
  {
   "start": 1486.5,
   "end": 1492.8,
   "text": "That um that the government gets has to pay less taxes if they hire dei hires and it's like the"
  },
  {
   "start": 1492.8,
   "end": 1498.2,
   "text": "Government paying taxes to itself doesn't make any sense and then other people yapping and then but I"
  },
  {
   "start": 1498.2,
   "end": 1502.92,
   "text": "Remember sam cedar saying it one more he's like yeah I've got the impression I'm talking to people"
  },
  {
   "start": 1502.92,
   "end": 1512.92,
   "text": "Who um who are just um programmed they're just repeating talking points from their little their"
  },
  {
   "start": 1512.92,
   "end": 1517.34,
   "text": "Little enclave of where they're getting information from and they and they're just saying stuff like"
  },
  {
   "start": 1517.34,
   "end": 1523.04,
   "text": "It's like it's true you know like like that uh social security is a ponzi scheme and so why would"
  },
  {
   "start": 1523.04,
   "end": 1528.9,
   "text": "You have the government pay pay pay the old people to live and instead of the government teach everybody"
  },
  {
   "start": 1528.9,
   "end": 1533.84,
   "text": "How to how to save up for themselves and it's like wait you want the government to teach everybody"
  },
  {
   "start": 1533.84,
   "end": 1537.76,
   "text": "To save for yourself now now you're now you're relying on the government more than"
  },
  {
   "start": 1537.76,
   "end": 1544.0,
   "text": "More than uh we were before when the government would just give you money and you know and then"
  },
  {
   "start": 1544.0,
   "end": 1549.18,
   "text": "And that and so anyways you have to know history because yeah what he was saying was they're they're"
  },
  {
   "start": 1549.18,
   "end": 1555.82,
   "text": "Just oh yeah they do these what about isms so they invent these like these like fantasy worlds"
  },
  {
   "start": 1555.82,
   "end": 1560.94,
   "text": "You know like they they bring in um you start talking about how everybody deserves health care and"
  },
  {
   "start": 1560.94,
   "end": 1565.52,
   "text": "Stuff and then they talk about how like well taxes are too high in scandinavia and what about"
  },
  {
   "start": 1565.52,
   "end": 1571.04,
   "text": "Scandinavia with all the taxes that they and so they invent some fantasy world like scandinavia is"
  },
  {
   "start": 1571.04,
   "end": 1576.08,
   "text": "All falling apart because they're all communism and they don't have any freedoms and and then they"
  },
  {
   "start": 1576.08,
   "end": 1581.46,
   "text": "Just create a world that doesn't exist that never did exist and the reason that they do that is"
  },
  {
   "start": 1581.46,
   "end": 1586.34,
   "text": "Because they don't know history like if people knew history then when then when you go into the"
  },
  {
   "start": 1586.34,
   "end": 1592.88,
   "text": "What about isms you're doing a real what about ism like what about 1940 39 or what about"
  },
  {
   "start": 1592.88,
   "end": 1600.0,
   "text": "1643 or when the black plague came out in 1348 it's like and then this happened and then and"
  },
  {
   "start": 1600.0,
   "end": 1604.14,
   "text": "There's no reason why we shouldn't be able to know enough history to do the what about isms that way"
  },
  {
   "start": 1604.14,
   "end": 1608.86,
   "text": "And then you don't have to create these fantasy worlds where these where well then we'll become"
  },
  {
   "start": 1608.86,
   "end": 1615.76,
   "text": "We'll become all uh communist and then we'll lose our freedoms because we're all communist with all of"
  },
  {
   "start": 1615.76,
   "end": 1622.32,
   "text": "The uh uh health care that we have and then we'll and then it's my freedom to not have to make a youtube"
  },
  {
   "start": 1622.32,
   "end": 1627.56,
   "text": "Video what are you telling me to take a test for you know it's just just bouncing around whatever's"
  },
  {
   "start": 1627.56,
   "end": 1637.04,
   "text": "Convenient for you to to like uh say your talking point and like and like uh what you're told to say"
  },
  {
   "start": 1637.04,
   "end": 1642.58,
   "text": "Like that you know rich people get to keep all their money and not get taxed and stuff so anyway um"
  },
  {
   "start": 1642.58,
   "end": 1654.35,
   "text": "Yeah so um uh there has to be like a true meritocracy and so that's why I designed my history test"
  },
  {
   "start": 1654.35,
   "end": 1661.13,
   "text": "You do well in the history test you get your your ubi you get your ubi you're living a pretty nice life"
  },
  {
   "start": 1661.13,
   "end": 1669.51,
   "text": "And you're not so if you can make everybody like not cost the government anything be positive influences"
  },
  {
   "start": 1669.51,
   "end": 1677.25,
   "text": "To everybody else um then then then that's a that's a good citizen you know as opposed to a citizen"
  },
  {
   "start": 1677.25,
   "end": 1681.89,
   "text": "Who's always trying to attack somebody else because you don't like them like michael knoll saying that"
  },
  {
   "start": 1681.89,
   "end": 1689.47,
   "text": "Any only fans girls should get treated like a school shooter quoting exactly and um you know like like"
  },
  {
   "start": 1689.47,
   "end": 1693.73,
   "text": "Maybe you should get a life maybe he's people are obsessed with people they don't like because"
  },
  {
   "start": 1693.73,
   "end": 1699.53,
   "text": "They don't have enough stuff so going on in their own lives so like yeah so like if I could like"
  },
  {
   "start": 1699.53,
   "end": 1703.75,
   "text": "Just get paid to ride my bike all day long and listen to audiobooks I'd be the happiest motherfucker"
  },
  {
   "start": 1703.75,
   "end": 1709.19,
   "text": "Ever and that wouldn't cost anything and then I could I could teach people what I know online"
  },
  {
   "start": 1709.19,
   "end": 1714.27,
   "text": "So why don't you give me the money for that oh because it's not because you don't understand the"
  },
  {
   "start": 1714.27,
   "end": 1718.09,
   "text": "Concept of that maybe as a rich person helping me you just get jealous of me because now I'm having"
  },
  {
   "start": 1718.09,
   "end": 1723.17,
   "text": "A better life than you because it's more fun to just be in shape and have fun riding a bike all day"
  },
  {
   "start": 1723.17,
   "end": 1728.89,
   "text": "Long and learning but you're here like like clamoring to make more money like and maybe that's"
  },
  {
   "start": 1728.89,
   "end": 1734.41,
   "text": "Why you don't want to give me money you know so so yeah if we could just convince everybody that"
  },
  {
   "start": 1734.41,
   "end": 1739.15,
   "text": "That's the best way to go then you and then you can those people are the people who get to be"
  },
  {
   "start": 1739.15,
   "end": 1744.75,
   "text": "The aristocracy you know and and if everybody has enough money to survive then it wouldn't be"
  },
  {
   "start": 1744.75,
   "end": 1750.47,
   "text": "This like elite what's it called elite overproduction battle clamoring over each other because if you"
  },
  {
   "start": 1750.47,
   "end": 1754.89,
   "text": "Don't make it then you'll starve your kids are going to starve and so if everybody has enough"
  },
  {
   "start": 1754.89,
   "end": 1759.17,
   "text": "Money to survive then there won't be as much pressure to be at the top and then the people"
  },
  {
   "start": 1759.17,
   "end": 1762.83,
   "text": "At the top are the people who actually deserve to be there who actually do care about other people"
  },
  {
   "start": 1762.83,
   "end": 1768.69,
   "text": "And do spend their time sitting around thinking about history and policy because history and policy"
  },
  {
   "start": 1768.69,
   "end": 1775.81,
   "text": "Correct policy making are the same exact thing because history is the story of what we did and what the"
  },
  {
   "start": 1775.81,
   "end": 1783.97,
   "text": "Results were what what decisions we made politically and what the results were that's history and so if"
  },
  {
   "start": 1783.97,
   "end": 1788.61,
   "text": "You knew all of that you could go you could live now as a policy maker and go well if I make this"
  },
  {
   "start": 1788.61,
   "end": 1793.67,
   "text": "Policy this will happen because I know history as opposed to somebody like donald trump who doesn't"
  },
  {
   "start": 1793.67,
   "end": 1798.77,
   "text": "Know any history thinks that colorado borders with mexico and there were airports during the war of"
  },
  {
   "start": 1798.77,
   "end": 1807.91,
   "text": "Independence and on and on um of course somebody like that is gonna like arbitrarily increase tariffs"
  },
  {
   "start": 1807.91,
   "end": 1811.63,
   "text": "And try to annex all these other countries because they want to do something that nobody else did"
  },
  {
   "start": 1811.63,
   "end": 1817.73,
   "text": "Because that makes him the shit the mover and shaker um because he doesn't he doesn't know history he"
  },
  {
   "start": 1817.73,
   "end": 1823.03,
   "text": "Doesn't know that he's doing the same exact thing that like commodus and caligula did trump wants to"
  },
  {
   "start": 1823.03,
   "end": 1830.11,
   "text": "Rename the gulf of mexico of america well commodus wanted to rename rome to commodium trump wants to"
  },
  {
   "start": 1830.11,
   "end": 1838.43,
   "text": "Make it like a like a kingdom again caligula wanted to make a statue of himself in israel so that they"
  },
  {
   "start": 1838.43,
   "end": 1842.57,
   "text": "So that the israelites would would worship him as god instead of that jehovah person"
  },
  {
   "start": 1842.57,
   "end": 1848.51,
   "text": "And so trump wants to talks about him in the third person and makes golden statues of himself I mean"
  },
  {
   "start": 1848.51,
   "end": 1854.45,
   "text": "You could go on and on and on I did a three and a half hour long video saying I hope trump drives"
  },
  {
   "start": 1854.45,
   "end": 1859.43,
   "text": "The coronavirus joe rogan and I spent three and a half hours talking about all the parallels between"
  },
  {
   "start": 1859.43,
   "end": 1866.85,
   "text": "Trump and all of the most worst people in history because I know my history and so basically the"
  },
  {
   "start": 1866.85,
   "end": 1872.29,
   "text": "Question is what do what do I think about donald trump and doing all of this trying to annex countries and"
  },
  {
   "start": 1872.29,
   "end": 1879.65,
   "text": "Doing tariffs well it's he's he he's taking it it's like chainsaw diplomacy he doesn't know what the"
  },
  {
   "start": 1879.65,
   "end": 1885.77,
   "text": "Hell he's doing and he's just chainsawing it but I think like like subconsciously maybe we all"
  },
  {
   "start": 1885.77,
   "end": 1894.09,
   "text": "Like that's kind of like how humans change anyway like we had to have a world war ii in order to figure"
  },
  {
   "start": 1894.09,
   "end": 1899.55,
   "text": "Out that we needed to help other countries you know boost other countries with the marshall plan"
  },
  {
   "start": 1899.55,
   "end": 1908.29,
   "text": "And uh helping you know build up our our ex-enemies um japan and germany and then you know helping the"
  },
  {
   "start": 1908.29,
   "end": 1915.45,
   "text": "Other countries or um learning how to tax the rich 90 you know we had a war for that and so maybe we"
  },
  {
   "start": 1915.45,
   "end": 1924.21,
   "text": "Need growing pains we need to throw in a bunch of tariffs to shake it up to force people to try to"
  },
  {
   "start": 1924.21,
   "end": 1937.72,
   "text": "Build our own things you know even if it causes um economic turmoil um um because I do personally"
  },
  {
   "start": 1937.72,
   "end": 1943.68,
   "text": "Would like to see stuff built in america um but you know trump himself he's a pair of a hypocrite"
  },
  {
   "start": 1943.68,
   "end": 1949.92,
   "text": "Somebody um somebody uh the the maga shirts they found out the maga shirts are all made in china"
  },
  {
   "start": 1949.92,
   "end": 1958.52,
   "text": "And like uh nicaragua and stuff but um so anyways so what do I think about in tariffs in general well"
  },
  {
   "start": 1958.52,
   "end": 1963.56,
   "text": "Yeah I think they could be okay but the question was what do I think about the tariffs of trump in the"
  },
  {
   "start": 1963.56,
   "end": 1970.58,
   "text": "Light of him trying to annex all these countries and I think it's him just trying to do his chain"
  },
  {
   "start": 1970.58,
   "end": 1977.54,
   "text": "Which in the past has always destroyed countries you know but things are a little bit different"
  },
  {
   "start": 1977.54,
   "end": 1982.54,
   "text": "Now and that we're all connected we're all more and more intelligent so hopefully what it will do"
  },
  {
   "start": 1982.54,
   "end": 1989.08,
   "text": "Is it will just wake up everybody to realize that um we're all a bunch of stooges when we"
  },
  {
   "start": 1989.08,
   "end": 1995.14,
   "text": "And brainwashed idiot monkeys when we start saying stuff like but the rich people should should keep all"
  },
  {
   "start": 1995.14,
   "end": 1999.34,
   "text": "Their hard-earned money are you trying to say that the rich can't keep their money it's like yes I am"
  },
  {
   "start": 1999.34,
   "end": 2004.88,
   "text": "Trying to say that the rich can't keep their money yes I am saying tax them 90 yes I am saying there"
  },
  {
   "start": 2004.88,
   "end": 2010.72,
   "text": "Should be no billionaires and so you know nobody wants to agree with you they still think that"
  },
  {
   "start": 2010.72,
   "end": 2015.62,
   "text": "Milan musk is a genius and all the rich people should keep them okay fine maybe we need to just"
  },
  {
   "start": 2015.62,
   "end": 2022.1,
   "text": "Let them destroy the government and the economy and rob everybody blind and get richer and then crash"
  },
  {
   "start": 2022.1,
   "end": 2027.34,
   "text": "And then for us to be like oh right rich people aren't the aren't the answer it's smart people"
  },
  {
   "start": 2027.34,
   "end": 2031.48,
   "text": "But not smart rich people how about smart hard-working people but not smart hard-working"
  },
  {
   "start": 2031.48,
   "end": 2037.86,
   "text": "People who who got their merits from like somebody liking them because they're good butt lickers you"
  },
  {
   "start": 2037.86,
   "end": 2042.78,
   "text": "Know because they went to the right school but because they are got good grades but because they"
  },
  {
   "start": 2042.78,
   "end": 2047.5,
   "text": "Have a good website and they and they got good grades on the standardized website that everybody"
  },
  {
   "start": 2047.5,
   "end": 2052.3,
   "text": "Can take over and over again you know so that's why I made these history sites these history tests"
  },
  {
   "start": 2052.3,
   "end": 2063.7,
   "text": "So anyways that's why that's what I think about that so if you uh canine 365 um either like my"
  },
  {
   "start": 2063.7,
   "end": 2069.0,
   "text": "Video or say that you liked it but if you don't do one of the two I'm not going to do any more of your"
  },
  {
   "start": 2069.0,
   "end": 2074.62,
   "text": "Uh request videos okay you gotta you gotta you gotta do a favor for me because I just did a favor for"
  },
  {
   "start": 2074.62,
   "end": 2080.98,
   "text": "You so either like it or say hey I liked it so that I can see that you said you liked it and then I can"
  },
  {
   "start": 2080.98,
   "end": 2084.68,
   "text": "See that there's either a like there or there's not a like there and then I can prove that oh look"
  },
  {
   "start": 2084.68,
   "end": 2091.22,
   "text": "Youtube does take away the likes when you do that so anyway there's my video uh and thanks for the"
  },
  {
   "start": 2091.22,
   "end": 2093.86,
   "text": "Request I'll do another one if anybody wants later"
  }
 ]
}