{
 "youtube_id": "KPaHIjkBaao",
 "title": "3/22/19 Google Earthing Mountains of Boulder still",
 "url": "https://youtu.be/KPaHIjkBaao",
 "published_at": "2019-03-22",
 "channel": "Kyle Pounds (channel 2)",
 "enrichment": null,
 "claims": [],
 "transcript": [
  {
   "start": 0.62,
   "end": 10.9,
   "text": "So, it's March 22nd, 2019, Friday, 2.43 p.m., and daily vlog living in Boulder."
  },
  {
   "start": 11.6,
   "end": 18.06,
   "text": "I'm just about to go to my mother's house in a half hour because I have to do things for her, find things."
  },
  {
   "start": 18.82,
   "end": 23.18,
   "text": "I'm kind of high off of my reefer gummies."
  },
  {
   "start": 25.36,
   "end": 29.88,
   "text": "That's all I have left on reefer gummies, and then I'm out."
  },
  {
   "start": 30.62,
   "end": 31.66,
   "text": "Then I have to quit."
  },
  {
   "start": 33.04,
   "end": 34.6,
   "text": "So, I finished my mountains."
  },
  {
   "start": 34.92,
   "end": 39.16,
   "text": "I went to mountain 400, and now I'm doing the filler in mountains, so it's like 50 or whatever."
  },
  {
   "start": 39.46,
   "end": 53.5,
   "text": "But once I got to the inner part of the alphabet, I could find other mountains that I could copy and paste off of and modify slightly."
  },
  {
   "start": 53.62,
   "end": 55.2,
   "text": "So, it was going by a little bit faster."
  },
  {
   "start": 55.78,
   "end": 57.76,
   "text": "I wasn't having to trace everything from scratch."
  },
  {
   "start": 57.76,
   "end": 60.04,
   "text": "So, yeah."
  },
  {
   "start": 60.18,
   "end": 60.74,
   "text": "But, yeah."
  },
  {
   "start": 60.84,
   "end": 70.94,
   "text": "I think I can finish these mountains and stay on track and finish all these 400 mountains and the roots out there and back and make the individual files of them."
  },
  {
   "start": 71.02,
   "end": 83.1,
   "text": "And then the file of the – where it's just the – like of each mountain of the – broken up into three different colors, but then also each mountain for their own colors and all that stuff."
  },
  {
   "start": 83.1,
   "end": 92.7,
   "text": "So, yeah, in just a few days, I'll be able – so I think I was on my one-week ATA, so I'm good."
  },
  {
   "start": 92.7,
   "end": 109.28,
   "text": "And then after that, I'm going to fix it up on the page, on the web page, make it by – after organizing it alphabetically, then do it by height and then by running percentage, I guess."
  },
  {
   "start": 109.28,
   "end": 114.72,
   "text": "And, yeah, so – and then I can move on to the other things and see how those are doing, you know."
  },
  {
   "start": 115.16,
   "end": 115.8,
   "text": "I'm in the mood."
  },
  {
   "start": 115.96,
   "end": 131.92,
   "text": "If I – if I – the good thing is if I stay on a high – on a fast pace and I get done with – I knock something out from limbo to pretty much done in two weeks or a week, then I'll – it'll motivate me to do the next one like that, you know."
  },
  {
   "start": 131.92,
   "end": 139.76,
   "text": "And then maybe I can get the next one knocked out in two weeks to two weeks and then – and then I'll go back to Rome and I can do that too and all of them, you know."
  },
  {
   "start": 140.7,
   "end": 149.52,
   "text": "So after, like, all said and done, just after another year or two, I should get my – my – definitely get my website to the next level for sure."
  },
  {
   "start": 149.52,
   "end": 161.9,
   "text": "And then at that point, you can start writing, writing, and that's the real – that's the real – the icing on the cake."
  },
  {
   "start": 162.36,
   "end": 165.6,
   "text": "So I was – I finished all my James Bond movies."
  },
  {
   "start": 165.72,
   "end": 170.88,
   "text": "I'm not listening to anything else because I'm just too high, really, off of these edibles, you know."
  },
  {
   "start": 170.94,
   "end": 172.12,
   "text": "You get really high off the edibles."
  },
  {
   "start": 173.34,
   "end": 178.46,
   "text": "It's like you're not high enough and then all of a sudden you're too high and then you're like – and then you're like, wait, you're not high enough and then you're too high."
  },
  {
   "start": 178.46,
   "end": 185.62,
   "text": "It's like trying to – it's like trying to, you know, do Google Earth with a really bad mouse connection, you know."
  },
  {
   "start": 186.26,
   "end": 191.7,
   "text": "Trying to write a book where each time you type it, you have to wait 10 seconds for the words to appear, you know."
  },
  {
   "start": 193.14,
   "end": 195.62,
   "text": "But – and overall, it's more expensive or a bit."
  },
  {
   "start": 196.74,
   "end": 200.96,
   "text": "You know, if I was just a little bit more richer, then I could have formed to be high all the time."
  },
  {
   "start": 201.6,
   "end": 206.9,
   "text": "Anybody who makes a reasonable amount of money should definitely be only getting high off the edibles and –"
  },
  {
   "start": 206.9,
   "end": 212.1,
   "text": "Because I'm having an asthma attack right now and I haven't – I haven't had a reefer for shit for a week or whatever."
  },
  {
   "start": 212.28,
   "end": 219.5,
   "text": "So it's like, you know, so – but they say that after seven years, your body reinvents itself, so –"
  },
  {
   "start": 219.5,
   "end": 222.64,
   "text": "Recreates every single one of the cells, so, you know."
  },
  {
   "start": 223.12,
   "end": 228.94,
   "text": "I won't have any black lung left after seven years from the last time I had a reefer, so I'll be good."
  },
  {
   "start": 228.94,
   "end": 233.74,
   "text": "But, um, so, yeah, and then I watched – did you, Bruce Lee?"
  },
  {
   "start": 234.64,
   "end": 242.8,
   "text": "I just did a classic movie kick, and so right now I'm doing – I think I was just about to start to kill Bill,"
  },
  {
   "start": 242.86,
   "end": 248.34,
   "text": "But my roommate bought 12 beers, and he says six of them are for me, so I was like, okay."
  },
  {
   "start": 248.72,
   "end": 253.16,
   "text": "He's like, yeah, isn't it badass to drink beer now that you're not as high?"
  },
  {
   "start": 253.16,
   "end": 260.1,
   "text": "And I'm like, oh, right, yeah, so I'll just drink beer as I'm running out of reefer gummies."
  },
  {
   "start": 260.54,
   "end": 261.82,
   "text": "Ooh, 4.20, maybe that's it."
  },
  {
   "start": 261.9,
   "end": 262.42,
   "text": "Okay, later."
  }
 ]
}