{
 "youtube_id": "S_ASypfCleA",
 "title": "Living in the Van Vlog 12-2-2011",
 "url": "https://youtu.be/S_ASypfCleA",
 "published_at": "2011-12-02",
 "channel": "Kyle Pounds (main)",
 "enrichment": null,
 "claims": [],
 "transcript": [
  {
   "start": 0.0,
   "end": 4.88,
   "text": "Hello, living in the Vaughan V-Log, the 2nd of December."
  },
  {
   "start": 6.04,
   "end": 13.4,
   "text": "It is 11.21 in the morning. I slept in because I had insomnia all night long."
  },
  {
   "start": 13.64,
   "end": 19.24,
   "text": "I listened to the first book of the history of Ireland yesterday."
  },
  {
   "start": 19.66,
   "end": 20.96,
   "text": "I didn't really remember much of it."
  },
  {
   "start": 23.6,
   "end": 29.83,
   "text": "But I was listening to it all night, and I really, really, really, really, really like that method, man."
  },
  {
   "start": 29.83,
   "end": 37.37,
   "text": "And from now on, I'm going to be listening to my history stuff, like, all night, man."
  },
  {
   "start": 37.99,
   "end": 39.53,
   "text": "Until the book's over, you know."
  },
  {
   "start": 39.81,
   "end": 42.65,
   "text": "Because I was already dozing off by the time the book ended."
  },
  {
   "start": 42.77,
   "end": 47.83,
   "text": "But I don't even care if I don't, if I don't, um..."
  },
  {
   "start": 47.83,
   "end": 50.17,
   "text": "Oh, God, what is the deal, man?"
  },
  {
   "start": 50.37,
   "end": 55.83,
   "text": "I must be, like, on some, like, really steep ass fucking..."
  },
  {
   "start": 57.41,
   "end": 58.59,
   "text": "Um, yeah, dude."
  },
  {
   "start": 58.59,
   "end": 62.29,
   "text": "Or maybe the surface is really slippery from something on it."
  },
  {
   "start": 63.37,
   "end": 68.23,
   "text": "Um, yeah, even if I don't understand all of it, man."
  },
  {
   "start": 68.35,
   "end": 76.67,
   "text": "Because, um, because, uh, you know, it's just music to my ears, and you understand some of it."
  },
  {
   "start": 76.73,
   "end": 78.39,
   "text": "At least you know the general gist."
  },
  {
   "start": 78.59,
   "end": 82.13,
   "text": "And then you know, like, what chapters you want to go back to."
  },
  {
   "start": 82.13,
   "end": 87.11,
   "text": "That's one of the things that you get, that you understand the first time you run through a, an audio book."
  },
  {
   "start": 87.15,
   "end": 91.21,
   "text": "Is, um, you remember, you know, what the chapters are."
  },
  {
   "start": 91.27,
   "end": 97.23,
   "text": "And it actually gave me the idea to bust up the chapters and put them into, you know, the various sections of, uh, subject."
  },
  {
   "start": 97.23,
   "end": 103.01,
   "text": "So that if you want to do a subject, you just do all the different books about that subject, you know."
  },
  {
   "start": 103.09,
   "end": 107.61,
   "text": "You do a doc, you do the documentary, you do the Wikipedia article, you do all the different audio books."
  },
  {
   "start": 107.73,
   "end": 112.09,
   "text": "Because, so anyways, um, that's, that's coming up next."
  },
  {
   "start": 112.17,
   "end": 115.13,
   "text": "But yeah, I just want to hammer through the history of Ireland, because it's so long."
  },
  {
   "start": 115.13,
   "end": 119.49,
   "text": "And there's this one book called The Decline and Fall of the Roman Empire that I want to listen to."
  },
  {
   "start": 119.73,
   "end": 122.21,
   "text": "I'm really interested, like, in the Roman Empire stuff, so."
  },
  {
   "start": 123.03,
   "end": 128.69,
   "text": "Um, yeah, but I was up, I had insomnia last night, and I was up all night."
  },
  {
   "start": 128.91,
   "end": 134.13,
   "text": "Plus I was kind of, I think one reason I had insomnia was I was up too late."
  },
  {
   "start": 134.45,
   "end": 141.25,
   "text": "Like, if, if I go to bed in my window, you know, when I first get groggy, and I first get tired, and I'm like, let's go."
  },
  {
   "start": 141.25,
   "end": 145.03,
   "text": "So, I, um, and I go to bed, I can fall asleep."
  },
  {
   "start": 145.11,
   "end": 150.85,
   "text": "But if I stay up, and I push myself, and I'm groggy, and I suffer through, and then I go to bed, I can't."
  },
  {
   "start": 150.89,
   "end": 157.11,
   "text": "Because, like, I guess second wind kicks in, or adrenaline, I don't know what it is, but extra energy has to kick in."
  },
  {
   "start": 157.27,
   "end": 159.83,
   "text": "And, and then I'm running on that, and I can't get to sleep."
  },
  {
   "start": 159.95,
   "end": 163.49,
   "text": "So, like, maybe I should have gotten to sleep earlier last night, but whatever."
  },
  {
   "start": 164.57,
   "end": 168.43,
   "text": "Um, it's cool to just lay in bed all morning long."
  },
  {
   "start": 168.43,
   "end": 171.85,
   "text": "And, um, I had some cool dreams, but I don't remember them."
  },
  {
   "start": 172.03,
   "end": 178.79,
   "text": "All I remember is that I was driving my car, like, through the snow, powering through people's, like, backyards and stuff."
  },
  {
   "start": 179.03,
   "end": 180.73,
   "text": "And that's all I remember."
  },
  {
   "start": 181.41,
   "end": 183.33,
   "text": "Um, so, there you go."
  },
  {
   "start": 184.19,
   "end": 188.81,
   "text": "Um, today I'm going to beeline it for the gym."
  },
  {
   "start": 189.31,
   "end": 196.49,
   "text": "The first thing I'm going to do is, um, um, man, I forgot to have my bowel movement last night at the supermarket."
  },
  {
   "start": 196.49,
   "end": 203.13,
   "text": "I have to remember to do that every night, because I'm eating more food now, and I'm passing more through me."
  },
  {
   "start": 203.33,
   "end": 206.15,
   "text": "And, yeah, plus I'm getting up so goddamn late."
  },
  {
   "start": 206.97,
   "end": 209.71,
   "text": "So I've got to move into the, uh, go to the gym right now."
  },
  {
   "start": 210.27,
   "end": 212.51,
   "text": "Do that before I have my breakfast and stuff."
  },
  {
   "start": 212.51,
   "end": 228.05,
   "text": "But, um, today I'm going to, um, go straight to the, um, the, uh, treadmill, because, um, because, um, the battery on my little computer is about to die."
  },
  {
   "start": 228.11,
   "end": 230.59,
   "text": "And that thing has to be charged up a long time to charge all the way."
  },
  {
   "start": 230.59,
   "end": 233.63,
   "text": "Um, yeah."
  },
  {
   "start": 234.91,
   "end": 239.72,
   "text": "And, um, yeah, and do some work on my site."
  },
  {
   "start": 239.82,
   "end": 242.36,
   "text": "You know, I'm pretty clear on some certain work I want to do."
  },
  {
   "start": 242.42,
   "end": 247.18,
   "text": "I was working on this king list of, um, of a certain country."
  },
  {
   "start": 247.3,
   "end": 247.7,
   "text": "What was it?"
  },
  {
   "start": 248.04,
   "end": 248.32,
   "text": "Bohemia."
  },
  {
   "start": 249.68,
   "end": 252.34,
   "text": "So that's pretty straightforward work that I need to do."
  },
  {
   "start": 252.38,
   "end": 255.66,
   "text": "And plus, you know, fixing up these other king lists that I just cut and pasted on my site."
  },
  {
   "start": 256.48,
   "end": 257.26,
   "text": "On my page."
  },
  {
   "start": 257.26,
   "end": 261.34,
   "text": "Um, and then work out all day long."
  },
  {
   "start": 261.42,
   "end": 264.14,
   "text": "Today's Friday, so they close at, like, 10 or something."
  },
  {
   "start": 264.34,
   "end": 267.24,
   "text": "So, definitely want to go straight into the gym."
  },
  {
   "start": 267.32,
   "end": 270.36,
   "text": "And then maybe after that, I'll go to that Safeway and work really late."
  },
  {
   "start": 270.86,
   "end": 274.32,
   "text": "And the gym closes at, like, 7 on the weekends."
  },
  {
   "start": 274.34,
   "end": 275.54,
   "text": "Or on Saturday, so."
  },
  {
   "start": 275.96,
   "end": 276.9,
   "text": "Or maybe it's 9."
  },
  {
   "start": 278.08,
   "end": 279.86,
   "text": "No, maybe it closes at 9 today."
  },
  {
   "start": 280.24,
   "end": 283.18,
   "text": "Goddammit, it closes at 9 today and, like, 7 or something tomorrow."
  },
  {
   "start": 283.72,
   "end": 286.36,
   "text": "So, yeah, I've got to beeline it to that gym and bust out."
  },
  {
   "start": 286.36,
   "end": 292.46,
   "text": "But, um, yeah, and, um, I have, like, 6 more days or something."
  },
  {
   "start": 292.56,
   "end": 293.3,
   "text": "5 more days."
  },
  {
   "start": 294.78,
   "end": 297.74,
   "text": "And when it expires here, I'll move up to the next gym."
  },
  {
   "start": 297.96,
   "end": 300.98,
   "text": "Oh, I'm going to drive down and pick up that credit card my mom sent me."
  },
  {
   "start": 301.0,
   "end": 303.24,
   "text": "Oh, yeah, and today maybe I'll transfer the money."
  },
  {
   "start": 303.34,
   "end": 306.94,
   "text": "I haven't been, I've been forgetting to transfer the money from my new credit card."
  },
  {
   "start": 307.34,
   "end": 308.82,
   "text": "And I don't even need the credit card."
  },
  {
   "start": 309.44,
   "end": 312.28,
   "text": "On the computer, so I don't have to pay interest anymore in that."
  },
  {
   "start": 313.9,
   "end": 315.18,
   "text": "Yeah, so that's that."
  },
  {
   "start": 315.32,
   "end": 315.84,
   "text": "Peace out."
  },
  {
   "start": 315.84,
   "end": 317.38,
   "text": "Hello, living in the van."
  },
  {
   "start": 317.48,
   "end": 320.96,
   "text": "V-log, 10th of November, December, 2011."
  },
  {
   "start": 321.5,
   "end": 328.22,
   "text": "Um, been running my car for 35 minutes, but I think that's good because I kind of had labor."
  },
  {
   "start": 328.66,
   "end": 333.32,
   "text": "Starting today, I think I just had, I was letting it run for 20 minutes, but it was just taking,"
  },
  {
   "start": 334.1,
   "end": 339.44,
   "text": "I was only letting it, like, um, charge by, uh, idling and stuff."
  },
  {
   "start": 339.44,
   "end": 343.54,
   "text": "So, you know, if you, if you idle it, you need like a half hour to charge the battery enough."
  },
  {
   "start": 343.62,
   "end": 346.66,
   "text": "So, anyway, I'm going to have to get gas tomorrow."
  },
  {
   "start": 346.94,
   "end": 348.62,
   "text": "I got gas the day that I came here."
  },
  {
   "start": 348.76,
   "end": 351.28,
   "text": "So, I don't know, once every week and a half or something, I get gas."
  },
  {
   "start": 351.28,
   "end": 354.66,
   "text": "So, I have to blaze from here in four more days or something."
  },
  {
   "start": 354.76,
   "end": 358.14,
   "text": "Let's see, I get the third, fourth, fifth, and sixth."
  },
  {
   "start": 358.82,
   "end": 360.46,
   "text": "So, I get four more days here."
  },
  {
   "start": 361.56,
   "end": 366.06,
   "text": "Um, got up really late because I was up really late last night."
  },
  {
   "start": 366.06,
   "end": 367.8,
   "text": "And then I had insomnia all night."
  },
  {
   "start": 369.16,
   "end": 370.82,
   "text": "Um, just a good old-fashioned insomnia."
  },
  {
   "start": 370.96,
   "end": 373.12,
   "text": "But I listened to my history of, uh, Ireland."
  },
  {
   "start": 373.24,
   "end": 374.14,
   "text": "I'm going to do some more today."
  },
  {
   "start": 374.3,
   "end": 375.54,
   "text": "I think I finished book three today."
  },
  {
   "start": 376.42,
   "end": 377.22,
   "text": "So, I did book four."
  },
  {
   "start": 377.6,
   "end": 378.9,
   "text": "Very boring stuff."
  },
  {
   "start": 379.02,
   "end": 380.1,
   "text": "Way too over-detailed."
  },
  {
   "start": 381.24,
   "end": 383.3,
   "text": "But, uh, you know, got to finish what I start."
  },
  {
   "start": 383.58,
   "end": 385.34,
   "text": "Um, to keep it organized."
  },
  {
   "start": 386.7,
   "end": 390.64,
   "text": "Um, went into the gym, walked for six miles."
  },
  {
   "start": 390.86,
   "end": 392.1,
   "text": "Then I went and worked out a little bit."
  },
  {
   "start": 392.78,
   "end": 394.14,
   "text": "But I could feel that I was tired."
  },
  {
   "start": 394.14,
   "end": 397.34,
   "text": "You know, I mean, even though I have plenty of muscle groups that are not tired,"
  },
  {
   "start": 397.5,
   "end": 399.84,
   "text": "My body generally feels kind of tired."
  },
  {
   "start": 400.34,
   "end": 403.42,
   "text": "Um, now one reason for that is because I didn't sleep much."
  },
  {
   "start": 403.44,
   "end": 406.76,
   "text": "Even though I slept in today, I kind of felt a little bit groggy."
  },
  {
   "start": 406.8,
   "end": 407.74,
   "text": "Like, I didn't sleep enough."
  },
  {
   "start": 407.82,
   "end": 410.56,
   "text": "So, yeah, I think my body's a little bit in recovery mode in general."
  },
  {
   "start": 412.28,
   "end": 414.92,
   "text": "Uh, because I had a pretty good lifting day like two days ago."
  },
  {
   "start": 415.08,
   "end": 419.04,
   "text": "So, um, I'm going to, um, I don't know, man."
  },
  {
   "start": 419.08,
   "end": 422.24,
   "text": "If I feel, if I go into the gym and I'm going to walk in the treadmill for six,"
  },
  {
   "start": 422.24,
   "end": 425.28,
   "text": "For three or six miles, and if I feel a little bit, and then lift a little bit,"
  },
  {
   "start": 425.34,
   "end": 429.12,
   "text": "But if I feel a little bit, not a hundred percent,"
  },
  {
   "start": 429.6,
   "end": 435.34,
   "text": "I might just go into the Starbucks and work all day because I'm really fired up about my, uh, site."
  },
  {
   "start": 435.62,
   "end": 439.38,
   "text": "Um, you know, I've been, I've been doing a lot of good work on it."
  },
  {
   "start": 439.46,
   "end": 442.02,
   "text": "There was a lot of time where I wasn't doing a lot of good work on my site"
  },
  {
   "start": 442.02,
   "end": 447.6,
   "text": "Because I was spending so much time collecting pictures, which took forever."
  },
  {
   "start": 447.78,
   "end": 452.38,
   "text": "Like, of all the battles, all the wars, all the battles, and all of the monarchs of all time."
  },
  {
   "start": 453.96,
   "end": 458.04,
   "text": "Um, as well as some other things, which I can't really remember, which took forever."
  },
  {
   "start": 458.12,
   "end": 459.26,
   "text": "That's when I was in Bellingham."
  },
  {
   "start": 459.46,
   "end": 461.62,
   "text": "So, it was kind of like I took some time off my site."
  },
  {
   "start": 461.62,
   "end": 465.96,
   "text": "Um, and, um, yes, but now I'm doing some good work."
  },
  {
   "start": 466.88,
   "end": 474.94,
   "text": "I did, uh, the, the king list of, uh, of, um, Bohemia, Hungary, Wallachia."
  },
  {
   "start": 475.58,
   "end": 480.1,
   "text": "Well, I was, I was, I'm like, it's kind of starting Wallachia now, and I did Transylvania."
  },
  {
   "start": 480.34,
   "end": 488.54,
   "text": "So, um, tomorrow I'm going to, um, yeah, I just love discovering these new kingdoms and princetons and stuff."
  },
  {
   "start": 488.54,
   "end": 493.24,
   "text": "You know, I mean, I wouldn't do a principality if it's, like, within, like, Germany, you know,"
  },
  {
   "start": 493.3,
   "end": 494.66,
   "text": "Like all the little duchies in Germany."
  },
  {
   "start": 494.74,
   "end": 498.68,
   "text": "I don't think I'll do that just because they were under the umbrella of the Holy Roman Empire."
  },
  {
   "start": 498.68,
   "end": 503.2,
   "text": "But, but if it's like, if that's, you know, the government that represented a country,"
  },
  {
   "start": 503.2,
   "end": 506.76,
   "text": "And the country doesn't have its own kingdom, like Romania, it didn't ever have its own kingdom,"
  },
  {
   "start": 506.86,
   "end": 511.46,
   "text": "It was just these principalities, then I'm going to include those in that, at least for now."
  },
  {
   "start": 512.9,
   "end": 516.3,
   "text": "Um, but yeah, it's cool how it's coming together in my mind."
  },
  {
   "start": 516.3,
   "end": 519.86,
   "text": "I'm learning more history, you know, my sights coming together."
  },
  {
   "start": 521.32,
   "end": 523.54,
   "text": "Yeah, so then I went back and I walked another three miles."
  },
  {
   "start": 523.64,
   "end": 524.68,
   "text": "So I ended up walking nine miles."
  },
  {
   "start": 525.38,
   "end": 528.96,
   "text": "After I walked the six miles, I worked out for, I worked for an hour on the computer until the battery died."
  },
  {
   "start": 529.0,
   "end": 530.26,
   "text": "And I stretched a little bit, maybe a half hour."
  },
  {
   "start": 531.38,
   "end": 533.5,
   "text": "And, uh, yeah, and then it got to be late."
  },
  {
   "start": 533.56,
   "end": 539.14,
   "text": "It's like 11, 18 now, so I'm cooking up my, uh, yeah, for breakfast I had, uh,"
  },
  {
   "start": 539.14,
   "end": 542.48,
   "text": "I think I had oatmeal and fruit."
  },
  {
   "start": 542.92,
   "end": 544.1,
   "text": "Yeah, I had oatmeal and fruit."
  },
  {
   "start": 544.22,
   "end": 545.02,
   "text": "It took forever to eat."
  },
  {
   "start": 545.54,
   "end": 547.8,
   "text": "Because I had to wait for the oatmeal to cool down and then I'd eat it."
  },
  {
   "start": 548.42,
   "end": 551.46,
   "text": "And then for lunch I had rice and pumpkin that I cooked the other day."
  },
  {
   "start": 551.52,
   "end": 552.8,
   "text": "That pumpkin's taking forever to eat."
  },
  {
   "start": 553.04,
   "end": 554.22,
   "text": "I hope it's not getting, like, rotten."
  },
  {
   "start": 555.1,
   "end": 556.08,
   "text": "I don't know if I'll be able to do it again."
  },
  {
   "start": 556.12,
   "end": 557.18,
   "text": "I'm almost out of gas."
  },
  {
   "start": 557.18,
   "end": 559.86,
   "text": "So I have to buy, like, gas."
  },
  {
   "start": 560.02,
   "end": 561.62,
   "text": "Well, car gas too, but this gas."
  },
  {
   "start": 561.68,
   "end": 563.28,
   "text": "So maybe I'll buy this kind of gas tomorrow."
  },
  {
   "start": 563.46,
   "end": 565.6,
   "text": "I'll go into the REI or whatever."
  },
  {
   "start": 566.0,
   "end": 567.1,
   "text": "Dedicate that as tomorrow."
  },
  {
   "start": 568.9,
   "end": 570.08,
   "text": "And, uh, that's done."
  },
  {
   "start": 571.32,
   "end": 576.98,
   "text": "Yeah, so that's a can of beans, green peas, or green beans, you know, normal beans."
  },
  {
   "start": 577.1,
   "end": 578.44,
   "text": "I don't know what you call those, brown beans."
  },
  {
   "start": 579.34,
   "end": 580.38,
   "text": "And, uh, beets."
  },
  {
   "start": 581.26,
   "end": 583.4,
   "text": "So, beets, beans, and brown beans."
  },
  {
   "start": 583.54,
   "end": 586.58,
   "text": "So, I don't know if I'm going to be able to finish all that."
  },
  {
   "start": 586.58,
   "end": 588.74,
   "text": "But, um, oh man, I love it."
  },
  {
   "start": 588.76,
   "end": 589.74,
   "text": "It just cooks up so fast."
  },
  {
   "start": 589.82,
   "end": 591.7,
   "text": "I can't wait until I'm done with this damn rice."
  },
  {
   "start": 592.46,
   "end": 593.56,
   "text": "Which takes so long to cook."
  },
  {
   "start": 593.86,
   "end": 601.36,
   "text": "And then it's, it's, it's, it's, it's, and then it's going to be only canned fruit and vegetables and, um, eggs."
  },
  {
   "start": 601.94,
   "end": 602.84,
   "text": "At least in the wintertime."
  },
  {
   "start": 603.48,
   "end": 605.14,
   "text": "And, uh, oatmeal from here on out."
  },
  {
   "start": 605.28,
   "end": 609.58,
   "text": "You know, and, you know, if I see, like, a deal on strawberries, raw strawberries, I'll get some of those, you know."
  },
  {
   "start": 609.7,
   "end": 610.54,
   "text": "And maybe even grapes."
  },
  {
   "start": 612.2,
   "end": 615.82,
   "text": "But, uh, you know, there's even grapes, canned grapes I got here."
  },
  {
   "start": 616.58,
   "end": 617.34,
   "text": "So, uh, yeah."
  },
  {
   "start": 617.64,
   "end": 618.92,
   "text": "You know, grapes and strawberries are all good."
  },
  {
   "start": 618.96,
   "end": 619.54,
   "text": "I like those, but."
  },
  {
   "start": 620.2,
   "end": 622.4,
   "text": "Yeah, so, uh, tomorrow that's what I'm going to do."
  },
  {
   "start": 622.52,
   "end": 623.86,
   "text": "And today that's what I did."
  },
  {
   "start": 625.3,
   "end": 625.66,
   "text": "Um."
  },
  {
   "start": 627.12,
   "end": 628.08,
   "text": "That's about all, man."
  },
  {
   "start": 628.76,
   "end": 632.28,
   "text": "I listened to my history, I've been listening to my history of, uh, Ireland all day."
  },
  {
   "start": 632.46,
   "end": 635.08,
   "text": "Didn't really absorb a whole lot of it, but whatever."
  },
  {
   "start": 635.86,
   "end": 636.22,
   "text": "Um."
  },
  {
   "start": 638.02,
   "end": 638.86,
   "text": "And that's that."
  },
  {
   "start": 638.92,
   "end": 640.16,
   "text": "What else do I have to say?"
  },
  {
   "start": 640.26,
   "end": 640.72,
   "text": "Peace out."
  },
  {
   "start": 640.82,
   "end": 641.36,
   "text": "Doggy style."
  },
  {
   "start": 641.36,
   "end": 641.66,
   "text": "Um."
  },
  {
   "start": 641.66,
   "end": 642.42,
   "text": "And that's what I have to say."
  },
  {
   "start": 642.42,
   "end": 642.66,
   "text": "Um."
  },
  {
   "start": 642.66,
   "end": 643.0,
   "text": "And that's what I have to say."
  },
  {
   "start": 643.0,
   "end": 643.3,
   "text": "And that's what I have to say."
  },
  {
   "start": 643.3,
   "end": 643.88,
   "text": "And that's what I have to say."
  },
  {
   "start": 643.88,
   "end": 644.38,
   "text": "And that's what I have to say."
  },
  {
   "start": 644.38,
   "end": 644.84,
   "text": "And that's what I have to say."
  },
  {
   "start": 644.84,
   "end": 645.38,
   "text": "And that's what I have to say."
  },
  {
   "start": 645.38,
   "end": 645.92,
   "text": "And that's what I have to say."
  },
  {
   "start": 645.92,
   "end": 646.34,
   "text": "And that's what I have to say."
  },
  {
   "start": 646.34,
   "end": 646.84,
   "text": "And that's what I have to say."
  },
  {
   "start": 646.84,
   "end": 647.42,
   "text": "And that's what I have to say."
  },
  {
   "start": 647.42,
   "end": 648.42,
   "text": "And that's what I have to say."
  },
  {
   "start": 648.42,
   "end": 648.88,
   "text": "And that's what I have to say."
  },
  {
   "start": 648.88,
   "end": 649.42,
   "text": "And that's what I have to say."
  },
  {
   "start": 649.42,
   "end": 650.42,
   "text": "And that's what I have to say."
  },
  {
   "start": 650.42,
   "end": 650.84,
   "text": "And that's what I have to say."
  },
  {
   "start": 650.84,
   "end": 651.42,
   "text": "And that's what I have to say."
  },
  {
   "start": 651.42,
   "end": 652.42,
   "text": "And that's what I have to say."
  },
  {
   "start": 652.42,
   "end": 652.92,
   "text": "And that's what I have to say."
  }
 ]
}